rushia_dl/__init__.py
rushia_dl/cli.py
rushia_dl-1.0.4.dist-info/LICENSE
rushia_dl-1.0.4.dist-info/METADATA
rushia_dl-1.0.4.dist-info/WHEEL
rushia_dl-1.0.4.dist-info/entry_points.txt
rushia_dl-1.0.4.dist-info/top_level.txt
rushia_dl-1.0.4.dist-info/RECORD
