Metadata-Version: 2.1
Name: rushia-dl
Version: 1.0.4
Summary: Youtube video & audio download wrapper
Home-page: https://github.com/konono/rushia_dl
Author: konono
Author-email: kono@ms1.kononet.jp
License: MIT
Classifier: Development Status :: 4 - Beta
Classifier: License :: OSI Approved :: MIT License
Classifier: Programming Language :: Python :: 3.7
Classifier: Programming Language :: Python :: 3.8
Classifier: Programming Language :: Python :: 3.9
Classifier: Programming Language :: Python :: 3.10
Classifier: Programming Language :: Python :: 3.11
Requires-Python: <4,>=3.7
License-File: LICENSE
Requires-Dist: argparse
Requires-Dist: pathlib
Requires-Dist: yt-dlp
